LICENSE
MANIFEST.in
Pipfile
README.md
requirements.txt
setup.cfg
setup.py
argo/workflows/__init__.py
argo/workflows/client/__about__.py
argo/workflows/client/__init__.py
argo/workflows/client/api_client.py
argo/workflows/client/configuration.py
argo/workflows/client/exceptions.py
argo/workflows/client/rest.py
argo/workflows/client/api/__init__.py
argo/workflows/client/api/v1alpha1_api.py
argo/workflows/client/models/__init__.py
argo/workflows/client/models/google_protobuf_any.py
argo/workflows/client/models/grpc_gateway_runtime_stream_error.py
argo/workflows/client/models/io_k8s_api_policy_v1beta1_pod_disruption_budget_spec.py
argo/workflows/client/models/v1_affinity.py
argo/workflows/client/models/v1_aws_elastic_block_store_volume_source.py
argo/workflows/client/models/v1_azure_disk_volume_source.py
argo/workflows/client/models/v1_azure_file_volume_source.py
argo/workflows/client/models/v1_capabilities.py
argo/workflows/client/models/v1_ceph_fs_volume_source.py
argo/workflows/client/models/v1_cinder_volume_source.py
argo/workflows/client/models/v1_config_map_env_source.py
argo/workflows/client/models/v1_config_map_key_selector.py
argo/workflows/client/models/v1_config_map_projection.py
argo/workflows/client/models/v1_config_map_volume_source.py
argo/workflows/client/models/v1_container.py
argo/workflows/client/models/v1_container_port.py
argo/workflows/client/models/v1_create_options.py
argo/workflows/client/models/v1_csi_volume_source.py
argo/workflows/client/models/v1_downward_api_projection.py
argo/workflows/client/models/v1_downward_api_volume_file.py
argo/workflows/client/models/v1_downward_api_volume_source.py
argo/workflows/client/models/v1_empty_dir_volume_source.py
argo/workflows/client/models/v1_env_from_source.py
argo/workflows/client/models/v1_env_var.py
argo/workflows/client/models/v1_env_var_source.py
argo/workflows/client/models/v1_exec_action.py
argo/workflows/client/models/v1_fc_volume_source.py
bmlx_argo_workflows.egg-info/PKG-INFO
bmlx_argo_workflows.egg-info/SOURCES.txt
bmlx_argo_workflows.egg-info/dependency_links.txt
bmlx_argo_workflows.egg-info/not-zip-safe
bmlx_argo_workflows.egg-info/requires.txt
bmlx_argo_workflows.egg-info/top_level.txt
