Metadata-Version: 2.1
Name: bmlx-argo-workflows
Version: 1.0.5
Summary: Community Maintained Python client for Argo Workflows
Home-page: https://github.com/argoproj-labs/argo-client-python
Author: Yudi Xue, Marek Cermak
Author-email: binarycrayon@gmail.com, macermak@redhat.com
License: MIT
Platform: UNKNOWN
Classifier: Development Status :: 3 - Alpha
Classifier: Intended Audience :: Developers
Classifier: Intended Audience :: Information Technology
Classifier: License :: OSI Approved :: MIT License
Classifier: Operating System :: OS Independent
Classifier: Programming Language :: Python :: 3.6
Classifier: Programming Language :: Python :: 3.7
Classifier: Programming Language :: Python :: 3.8
Classifier: Topic :: Software Development
Classifier: Topic :: Utilities
